siti/__init__.py
siti/exc.py
siti/utils.py
siti/version.py
siti/http/__init__.py
siti/http/client.py
siti/http/oauth_token.py
siti/resources/__init__.py
siti/resources/base.py
siti/resources/ifpe/__init__.py
siti/resources/ifpe/base.py
siti/resources/ifpe/catalogos.py
siti/resources/ifpe/reportes.py
siti/resources/ifpe/seguimiento.py
siti/resources/ifpe/types.py
siti/resources/ifpe/r01/__init__.py
siti/resources/ifpe/r01/reporte_111.py
siti/resources/ifpe/r08/__init__.py
siti/resources/ifpe/r08/reporte_843.py
siti/resources/ifpe/r10/__init__.py
siti/resources/ifpe/r10/commons.py
siti/resources/ifpe/r10/reporte_10111.py
siti/resources/ifpe/r10/reporte_10121.py
siti/resources/ifpe/r13/__init__.py
siti/resources/ifpe/r13/commons.py
siti/resources/ifpe/r13/reporte_13111.py
siti/resources/ifpe/r13/reporte_13161.py
siti/resources/ifpe/r13/reporte_13211.py
siti/resources/ifpe/r13/reporte_13221.py
siti/resources/ifpe/r24/__init__.py
siti/resources/ifpe/r24/reporte_2471.py
siti/resources/ifpe/r24/reporte_2472.py
siti/resources/ifpe/r26/__init__.py
siti/resources/ifpe/r26/reporte_2610.py
siti/resources/ifpe/r26/reporte_2611.py
siti/resources/ifpe/r26/reporte_2612.py
siti/resources/ifpe/r26/reporte_2613.py
siti/resources/ifpe/r27/__init__.py
siti/resources/ifpe/r27/reporte_2701.py
siti/resources/ifpe/r36/__init__.py
siti/resources/ifpe/r36/reporte_3611.py
siti/resources/ifpe/r36/reporte_3612.py
siti/resources/ifpe/r36/reporte_3613.py
tests/__init__.py
tests/conftest.py
tests/test_utils.py
tests/http/__init__.py
tests/http/conftest.py
tests/http/test_client.py
aiositi_mex-0.0.4.dist-info/METADATA
aiositi_mex-0.0.4.dist-info/WHEEL
aiositi_mex-0.0.4.dist-info/top_level.txt
aiositi_mex-0.0.4.dist-info/RECORD
